LICENSE
README.md
setup.py
toyecc/ASN1.py
toyecc/AffineCurvePoint.py
toyecc/CRT.py
toyecc/CurveDB.py
toyecc/CurveOps.py
toyecc/CurveQuirks.py
toyecc/DivisionPolynomial.py
toyecc/DocInherit.py
toyecc/ECPrivateKey.py
toyecc/ECPublicKey.py
toyecc/EllipticCurve.py
toyecc/Exceptions.py
toyecc/FieldElement.py
toyecc/MontgomeryCurve.py
toyecc/PointOps.py
toyecc/Polynomial.py
toyecc/PrivKeyOps.py
toyecc/PubKeyOps.py
toyecc/Random.py
toyecc/ShortWeierstrassCurve.py
toyecc/Singleton.py
toyecc/Tools.py
toyecc/TwistedEdwardsCurve.py
toyecc/__init__.py
toyecc.egg-info/PKG-INFO
toyecc.egg-info/SOURCES.txt
toyecc.egg-info/dependency_links.txt
toyecc.egg-info/requires.txt
toyecc.egg-info/top_level.txt
toyecc/tests/CRTTests.py
toyecc/tests/CryptoOpsTests.py
toyecc/tests/CurveQuirkTests.py
toyecc/tests/CurveTests.py
toyecc/tests/DivPolyTests.py
toyecc/tests/ECTests.py
toyecc/tests/Ed25519BasicTests.py
toyecc/tests/Ed25519ExtdTests.py
toyecc/tests/Ed448BasicTests.py
toyecc/tests/FieldElementSqrtTests.py
toyecc/tests/FieldElementTests.py
toyecc/tests/FullTests.py
toyecc/tests/KeyLoadStoreTests.py
toyecc/tests/OpenSSLCurveTests.py
toyecc/tests/PointSerializationTests.py
toyecc/tests/PolyTests.py
toyecc/tests/TwEdMontConversionTests.py
toyecc/tests/TwEdMontDomainTests.py
toyecc/tests/TwistTests.py
toyecc/tests/XOnlyTests.py
toyecc/tests/__init__.py