Metadata-Version: 2.1
Name: toyecc
Version: 0.0.8
Summary: Elliptic Curve Cryptography playground/toolkit written in pure Python
Home-page: https://github.com/johndoe31415/toyecc
Author: Johannes Bauer
Author-email: joe@johannes-bauer.com
License: gpl-3.0
Download-URL: https://github.com/johndoe31415/toyecc/archive/v0.0.8.tar.gz
Keywords: elliptic,curve,cryptography,ed25519,ecdsa,ecdh,montgomery,edwards,weierstrass
Platform: UNKNOWN
Classifier: Development Status :: 5 - Production/Stable
Classifier: Intended Audience :: Developers
Classifier: License :: OSI Approved :: GNU General Public License v3 (GPLv3)
Classifier: Programming Language :: Python :: 3
Classifier: Programming Language :: Python :: 3 :: Only
Classifier: Programming Language :: Python :: 3.5
Classifier: Programming Language :: Python :: 3.6
Classifier: Programming Language :: Python :: 3.7
Classifier: Programming Language :: Python :: 3.8
Classifier: Programming Language :: Python :: 3.9
License-File: LICENSE
